{"@context":"https://schema.org/","@type":"Recipe","aggregateRating":{"@type":"AggregateRating","bestRating":"5","ratingCount":"1","ratingValue":"5","worstRating":"1"},"author":{"@type":"Person","name":"Advanced Mixology"},"cookTime":"","description":"Planter’s Punch is a cocktail that originated in Jamaica. But some people also believe that the drink originally originated at the Planter’s Hotel in South Carolina. And the first time that its recipe got issued in the\u0026amp;nbsp;London Magazine was in 1878. It is made with several juices, rum, sugar and grenadine syrup, and many more ingredients","image":["https://res.cloudinary.com/hsxfx8igq/image/upload/t_16x9_recipe_image,f_auto/v1626651002/recipe_kit_mdknaf.jpg","https://res.cloudinary.com/hsxfx8igq/image/upload/t_4x3_recipe_image,f_auto/v1626651002/recipe_kit_mdknaf.jpg","https://res.cloudinary.com/hsxfx8igq/image/upload/t_1x1_recipe_image,f_auto/v1626651002/recipe_kit_mdknaf.jpg"],"keywords":["planter's punch","planter's punch original recipe","planter's punch history","cocktail planters punch","planter's punch cocktail","planter's punch recipe","how to make planter's punch"],"name":"Planter\u0026#39;s Punch","nutrition":{"@type":"NutritionInformation","calories":"165","servingSize":"1"},"prepTime":"PT5M","recipeCategory":"\u0026lt;p\u0026gt;Cocktail Recipe\u0026lt;/p\u0026gt;","recipeCuisine":"","recipeIngredient":["3 oz dark rum","¾ oz fresh lime juice","1 oz simple syrup","1 tbsp grenadine","3 dashes Angostura bitters","Splash of soda water","Mint sprig for garnish"],"recipeInstructions":[{"@type":"HowToStep","name":"Gather all the ingredients and put them into a shaker with ice.","text":"Gather all the ingredients and put them into a shaker with ice.","url":"https://advancedmixology.com/blogs/art-of-mixology/planters-punch-cocktail-recipe#step-1"},{"@type":"HowToStep","name":"Now shake the shaker until the ice gets crushed and all the ingredients get chilled.","text":"Now shake the shaker until the ice gets crushed and all the ingredients get chilled.","url":"https://advancedmixology.com/blogs/art-of-mixology/planters-punch-cocktail-recipe#step-2"},{"@type":"HowToStep","name":"Now add a splash of soda water in a glass and then add all the chilled ingredients from the shaker into the glass.","text":"Now add a splash of soda water in a glass and then add all the chilled ingredients from the shaker into the glass.","url":"https://advancedmixology.com/blogs/art-of-mixology/planters-punch-cocktail-recipe#step-3"},{"@type":"HowToStep","name":"Now garnish the drink with Mint Sprig and serve.","text":"Now garnish the drink with Mint Sprig and serve.","url":"https://advancedmixology.com/blogs/art-of-mixology/planters-punch-cocktail-recipe#step-4"}],"recipeYield":"1","totalTime":"PT5M"}