{"@context":"https://schema.org/","@type":"Recipe","aggregateRating":{"@type":"AggregateRating","bestRating":"5","ratingCount":"1","ratingValue":"5","worstRating":"1"},"author":{"@type":"Person","name":"Advanced Mixology"},"cookTime":"","description":"The Strawberry Rhubarb\u0026amp;nbsp;Sangria recipe is perfect for any spring or summer occasion. This drink combines the best of two worlds–wine and fruit!  With only five ingredients, you can make this thrilling cocktail in no time. For those who are more adventurous, try adding a little\u0026amp;nbsp;vodka to take it up a notch! Whether you\u0026#39;re celebrating with friends or just want something delicious on a warm day, the Strawberry Rhubarb Sangria will be your new go-to drink. ","image":["","",""],"keywords":["Strawberry Rhubarb Sangria","Strawberry Rhubarb Sangria Recipe","Strawberry Rhubarb Sangria Cocktail","How To Strawberry Rhubarb Sangria","Strawberry Rhubarb Sangria Cocktail Recipe"],"name":"Strawberry Rhubarb Sangria","nutrition":{"@type":"NutritionInformation","servingSize":"1"},"prepTime":"PT5M","recipeCategory":"","recipeCuisine":"","recipeIngredient":["2 cups Rhubarb (diced or roughly chopped)","1 cup Water","1 cup Sugar","1 Bottle of White wine","½ cup Vodka","¼ cup St. Germaine Liquor","1 cup Strawberries, sliced","1 Lime, sliced"],"recipeInstructions":[{"@type":"HowToStep","name":"Make the rhubarb syrup by heating the water, rhubarb, and sugar in a pan.","text":"Make the rhubarb syrup by heating the water, rhubarb, and sugar in a pan.","url":"https://advancedmixology.com/blogs/art-of-mixology/strawberry-rhubarb-sangria-recipe#step-2"},{"@type":"HowToStep","name":"Cook for 5 minutes on medium-low heat until thick and pinkish.","text":"Cook for 5 minutes on medium-low heat until thick and pinkish.","url":"https://advancedmixology.com/blogs/art-of-mixology/strawberry-rhubarb-sangria-recipe#step-3"},{"@type":"HowToStep","name":"Strain the liquid to remove the rhubarb.","text":"Strain the liquid to remove the rhubarb.","url":"https://advancedmixology.com/blogs/art-of-mixology/strawberry-rhubarb-sangria-recipe#step-4"},{"@type":"HowToStep","name":"Refrigerate the strained liquid.","text":"Refrigerate the strained liquid.","url":"https://advancedmixology.com/blogs/art-of-mixology/strawberry-rhubarb-sangria-recipe#step-5"},{"@type":"HowToStep","name":"Mix the white wine, vodka, St. Germaine liquor, strawberries, and limes in a large pitcher.","text":"Mix the white wine, vodka, St. Germaine liquor, strawberries, and limes in a large pitcher.","url":"https://advancedmixology.com/blogs/art-of-mixology/strawberry-rhubarb-sangria-recipe#step-7"},{"@type":"HowToStep","name":"Add the chilled rhubarb syrup to the mixture.","text":"Add the chilled rhubarb syrup to the mixture.","url":"https://advancedmixology.com/blogs/art-of-mixology/strawberry-rhubarb-sangria-recipe#step-8"},{"@type":"HowToStep","name":"Refrigerate the sangria for at least 30 minutes or up to two days.","text":"Refrigerate the sangria for at least 30 minutes or up to two days.","url":"https://advancedmixology.com/blogs/art-of-mixology/strawberry-rhubarb-sangria-recipe#step-9"},{"@type":"HowToStep","name":"Serve with sliced strawberries or limes.","text":"Serve with sliced strawberries or limes.","url":"https://advancedmixology.com/blogs/art-of-mixology/strawberry-rhubarb-sangria-recipe#step-10"}],"recipeYield":"1","totalTime":"PT5M"}