{"@context":"https://schema.org","@type":"Recipe","aggregateRating":{"@type":"AggregateRating","bestRating":"5","ratingCount":1,"ratingValue":"3.5","worstRating":"0"},"author":"Jerry \"The Professor\" Thomas","datePublished":"2015-09-05 09:26:41","description":"This aniseed-flavoured mix tastes surprisingly tame but includes a shot of the notorious green fairy.","glassWare":"Martini glass","image":"https://cdn.diffords.com/contrib/stock-images/2018/05/5af2fad1b9883.jpg","keywords":["Drink","Cocktail","Recipe"],"name":"Absinthe Cocktail (Jerry Thomas) ","nutrition":{"@type":"NutritionInformation","calories":"145 calories"},"prepTime":"PT02M0S","recipeCategory":"Drink","recipeCuisine":"Cocktail","recipeIngredient":["30 ml Absinthe verte (green)","7.5 ml Anisette liqueur","1 Angostura or other aromatic bitters","45 ml Chilled water (reduce if wet ice)"],"recipeInstructions":[{"@type":"HowToStep","text":"SHAKE all ingredients with ice and fine strain into chilled glass"}],"recipeYield":"1","slug":"absinthe-cocktail-jerry-thomas","standardDrinks":"1.8","totalTime":"PT02M0S","url":"https://www.diffordsguide.com/en-au/cocktails/recipe/506/absinthe-cocktail-jerry-thomas"}