{"@context":"https://schema.org","@type":"Recipe","aggregateRating":{"@type":"AggregateRating","bestRating":"5","ratingCount":11,"ratingValue":"4.5","worstRating":"0"},"author":"Simon Difford","datePublished":"2021-09-17 11:11:04","description":"I've used a 50/50 mix of dry and bianco vermouths to add some (I believe) much-needed honeyed richness to the all-dry vermouth vintage recipe. Depending on your lemons and crème de mûre, the subtle richness added by splitting the vermouth in this way will hopefully help achieve a perfectly balanced cocktail.","glassWare":"Coupe glass","image":"https://cdn.diffords.com/contrib/stock-images/2021/09/61447f8beebe8.jpg","keywords":["Drink","Cocktail","Recipe"],"name":"Allegheny","nutrition":{"@type":"NutritionInformation","calories":"173 calories"},"prepTime":"PT04M0S","recipeCategory":"Drink","recipeCuisine":"Cocktail","recipeIngredient":["40 ml Whiskey - Bourbon whiskey","20 ml Dry vermouth","20 ml Bianco vermouth","10 ml Crème de mûre (blackberry liqueur)","10 ml Lemon juice (freshly squeezed)","1 Angostura or other aromatic bitters"],"recipeInstructions":[{"@type":"HowToStep","text":"SHAKE all ingredients with ice and strain into chilled glass"}],"recipeYield":"1","slug":"allegheny","standardDrinks":"1.9","totalTime":"PT04M0S","url":"https://www.diffordsguide.com/en-au/cocktails/recipe/9728/allegheny"}