{"@context":"https://schema.org","@type":"Recipe","aggregateRating":{"@type":"AggregateRating","bestRating":"5","ratingCount":9,"ratingValue":"3.5","worstRating":"0"},"author":"Maksym \"Maks\" Pazuniak","datePublished":"2019-09-05 15:38:35","description":"The name should perhaps serve as a warning, as should the whopping ounce-and-a-half of Angostura Bitters in this recipe, and intense Angostura flavour dominates this bittersweet lime sour.","glassWare":"Coupe glass","image":"https://cdn.diffords.com/contrib/stock-images/2019/09/5d72536b67e8f.jpg","keywords":["Drink","Cocktail","Recipe"],"name":"Angostura Sour","nutrition":{"@type":"NutritionInformation","calories":"71 calories"},"prepTime":"PT03M0S","recipeCategory":"Drink","recipeCuisine":"Cocktail","recipeIngredient":["45 ml Angostura or other aromatic bitters","30 ml Lime juice (freshly squeezed)","15 ml Sugar syrup 'rich' (2 sugar to 1 water, 65.0°brix)","15 ml Pasteurised egg white (or aquafaba)"],"recipeInstructions":[{"@type":"HowToStep","text":"SHAKE all ingredients with ice and strain back into shaker"},{"@type":"HowToStep","text":"DRY SHAKE (without ice) and fine strain into chilled glass"}],"recipeYield":"1","slug":"angostura-sour","standardDrinks":"1.6","totalTime":"PT03M0S","url":"https://www.diffordsguide.com/en-au/cocktails/recipe/4815/angostura-sour"}