{"@context":"https://schema.org","@type":"Recipe","aggregateRating":{"@type":"AggregateRating","bestRating":"5","ratingCount":11,"ratingValue":"4.0","worstRating":"0"},"author":"Simon Difford","datePublished":"2017-04-12 11:16:01","description":"Fortified bubble gum for the young at heart.","glassWare":"Martini glass","image":"https://cdn.diffords.com/contrib/stock-images/2018/05/5af2fc63c859c.jpg","keywords":["Drink","Cocktail","Recipe"],"name":"Banana Boomer","nutrition":{"@type":"NutritionInformation","calories":"263 calories"},"prepTime":"PT02M0S","recipeCategory":"Drink","recipeCuisine":"Cocktail","recipeIngredient":["30 ml Vodka","30 ml Crème de banane liqueur","15 ml Apricot (brandy) liqueur","15 ml Cherry brandy liqueur","22.5 ml Orange juice (freshly squeezed)","22.5 ml Pineapple juice (fresh pressed)"],"recipeInstructions":[{"@type":"HowToStep","text":"SHAKE all ingredients with ice and strain into chilled glass"}],"recipeYield":"1","slug":"banana-boomer","standardDrinks":"2.3","totalTime":"PT02M0S","url":"https://www.diffordsguide.com/en-au/cocktails/recipe/160/banana-boomer"}