{"@context":"https://schema.org","@type":"Recipe","aggregateRating":{"@type":"AggregateRating","bestRating":"5","ratingCount":1,"ratingValue":"3.5","worstRating":"0"},"author":"Simon Difford","datePublished":"2017-04-12 11:36:12","description":"Cider downstairs, Guinness upstairs","glassWare":"Boston glass","image":"https://cdn.diffords.com/contrib/stock-images/2018/05/5af2fd3919ceb.jpg","keywords":["Drink","Cocktail","Recipe"],"name":"Black \u0026 Velvet","nutrition":{"@type":"NutritionInformation","calories":"1131 calories"},"prepTime":"PT02M0S","recipeCategory":"Drink","recipeCuisine":"Cocktail","recipeIngredient":["1/2 Medium dry apple cider","1/2 Stout beer"],"recipeInstructions":[{"@type":"HowToStep","text":"POUR cider into chilled glass then FLOAT Guinness on top"}],"recipeYield":"1","slug":"black-and-velvet","standardDrinks":"2.6","totalTime":"PT02M0S","url":"https://www.diffordsguide.com/en-au/cocktails/recipe/549/black-and-velvet"}