{"@context":"https://schema.org","@type":"Recipe","aggregateRating":{"@type":"AggregateRating","bestRating":"5","ratingCount":24,"ratingValue":"4.0","worstRating":"0"},"author":"Roger Grüter","datePublished":"2020-08-07 07:51:58","description":"Two parts amaro to 1 part Islay single malt is a boundary-pushing recipe but with a splash of banana liqueur, the resulting cocktail is balanced and tasty.","glassWare":"Double old-fashioned","image":"https://cdn.diffords.com/contrib/stock-images/2020/08/5f2d182c00850.jpg","keywords":["Drink","Cocktail","Recipe"],"name":"Black Magic No.2","nutrition":{"@type":"NutritionInformation","calories":"255 calories"},"prepTime":"PT02M0S","recipeCategory":"Drink","recipeCuisine":"Cocktail","recipeIngredient":["60 ml Amaro - Montenegro","30 ml Whisky - Peated Scotch whisky","10 ml Crème de banane liqueur","2 Saline solution 4:1 (20g sea salt to 80g water)"],"recipeInstructions":[{"@type":"HowToStep","text":"STIR all ingredients with ice and strain into ice-filled glass (preferably over a chunk of block ice)"}],"recipeYield":"1","slug":"black-magic-no2","standardDrinks":"2.5","totalTime":"PT02M0S","url":"https://www.diffordsguide.com/en-au/cocktails/recipe/5584/black-magic-no2"}