{"@context":"https://schema.org","@type":"Recipe","aggregateRating":{"@type":"AggregateRating","bestRating":"5","ratingCount":12,"ratingValue":"4.5","worstRating":"0"},"author":"Phillip Jeffrey","datePublished":"2016-07-13 11:47:49","description":"An ostentatious little number.","glassWare":"Shot glass","image":"https://cdn.diffords.com/contrib/stock-images/2018/05/5af2fd7a3990f.jpg","keywords":["Drink","Cocktail","Recipe","Bling Bling"],"name":"Bling! Bling!","nutrition":{"@type":"NutritionInformation","calories":"69 calories"},"prepTime":"PT04M0S","recipeCategory":"Drink","recipeCuisine":"Cocktail","recipeIngredient":["7 Raspberries (fresh)","15 ml Vodka","15 ml Lime juice (freshly squeezed)","7.5 ml Sugar syrup 'rich' (2 sugar to 1 water, 65.0°brix)","15 ml Brut champagne or sparkling wine"],"recipeInstructions":[{"@type":"HowToStep","text":"MUDDLE raspberries in base of shaker"},{"@type":"HowToStep","text":"Add vodka, lime and sugar, SHAKE with ice and fine strain into glass"},{"@type":"HowToStep","text":"TOP with champagne"}],"recipeYield":"1","slug":"bling-bling","standardDrinks":"0.6","totalTime":"PT04M0S","url":"https://www.diffordsguide.com/en-au/cocktails/recipe/242/bling-bling"}