{"@context":"https://schema.org","@type":"Recipe","aggregateRating":{"@type":"AggregateRating","bestRating":"5","ratingCount":15,"ratingValue":"4.0","worstRating":"0"},"author":"David A. Embury","datePublished":"2016-07-18 13:55:01","description":"A beautifully balanced, flavoursome medley of sweet and sour.","glassWare":"Old-fashioned glass","image":"https://cdn.diffords.com/contrib/stock-images/2016/7/55/2016496131871b3b2de8e6a6b77a3edd8c88.jpg","keywords":["Drink","Cocktail","Recipe"],"name":"Bolero Sour","nutrition":{"@type":"NutritionInformation","calories":"170 calories"},"prepTime":"PT04M0S","recipeCategory":"Drink","recipeCuisine":"Cocktail","recipeIngredient":["30 ml White (charcoal-filtered) 1-4 year old light rum","30 ml Cognac (brandy)","15 ml Lime juice (freshly squeezed)","10 ml Orange juice (freshly squeezed)","10 ml Sugar syrup 'rich' (2 sugar to 1 water, 65.0°brix)","10 ml Pasteurised egg white (or aquafaba)"],"recipeInstructions":[{"@type":"HowToStep","text":"SHAKE all ingredients with ice and fine strain back into shaker"},{"@type":"HowToStep","text":"DRY SHAKE (without ice) and fine strain into an ice-filled glass"}],"recipeYield":"1","slug":"bolero-sour","standardDrinks":"1.9","totalTime":"PT04M0S","url":"https://www.diffordsguide.com/en-au/cocktails/recipe/284/bolero-sour"}