{"@context":"https://schema.org","@type":"Recipe","aggregateRating":{"@type":"AggregateRating","bestRating":"5","ratingCount":8,"ratingValue":"4.0","worstRating":"0"},"author":"Wayne Collins","datePublished":"2016-08-11 21:23:15","description":"Scotch whisky adds a delicately malty backbone to this zesty and fruity, delicately honeyed anytime cocktail.","glassWare":"Coupe glass","image":"https://cdn.diffords.com/contrib/stock-images/2020/09/5f4f5ce9cdb2d.jpg","keywords":["Drink","Cocktail","Recipe"],"name":"Capercaillie","nutrition":{"@type":"NutritionInformation","calories":"201 calories"},"prepTime":"PT04M0S","recipeCategory":"Drink","recipeCuisine":"Cocktail","recipeIngredient":["50 ml Blended Scotch whisky","12.5 ml Triple sec liqueur (40% alc./vol.)","10 ml Apricot (brandy) liqueur","25 ml Pineapple juice (fresh pressed)","12.5 ml Lemon juice (freshly squeezed)","10 ml Honey syrup (3 honey to 1 water)"],"recipeInstructions":[{"@type":"HowToStep","text":"SHAKE all ingredients with ice and fine strain into chilled glass"}],"recipeYield":"1","slug":"capercaillie","standardDrinks":"2.3","totalTime":"PT04M0S","url":"https://www.diffordsguide.com/en-au/cocktails/recipe/369/capercaillie"}