{"@context":"https://schema.org","@type":"Recipe","aggregateRating":{"@type":"AggregateRating","bestRating":"5","ratingCount":2,"ratingValue":"4.5","worstRating":"0"},"author":"Moe Aliaff","datePublished":"2017-01-04 08:26:48","description":"I had to boil a can of condensed milk for three hours to make the dulce de leche but its sweetened caramelised milk flavour is the heart of this unusual cocktail. Rum fortifies with banana, PX sherry and lemon all adding important elements.","glassWare":"Nick \u0026 Nora glass","image":"https://cdn.diffords.com/contrib/stock-images/2018/05/5af2fef239a8c.jpg","keywords":["Drink","Cocktail","Recipe"],"name":"Carousel","nutrition":{"@type":"NutritionInformation","calories":"152 calories"},"prepTime":"PT04M0S","recipeCategory":"Drink","recipeCuisine":"Cocktail","recipeIngredient":["50 ml Bacardi Carta Oro","30 ml *Special ingredient #1 (see above)","10 ml Pedro Ximénez sherry","5 ml Crème de banane liqueur","30 ml Lemon juice (freshly squeezed)","1 Salt"],"recipeInstructions":[{"@type":"HowToStep","text":"SHAKE all ingredients with ice and fine strain into chilled glass"},{"@type":"HowToStep","text":"\u003cstrong\u003e*Special ingredient #1\u003c/strong\u003e: Dulce de leche (30ml is approx"},{"@type":"HowToStep","text":"5 bar spoons)"}],"recipeYield":"1","slug":"carousel","standardDrinks":"1.5","totalTime":"PT04M0S","url":"https://www.diffordsguide.com/en-au/cocktails/recipe/3903/carousel"}