{"@context":"https://schema.org","@type":"Recipe","aggregateRating":{"@type":"AggregateRating","bestRating":"5","ratingCount":10,"ratingValue":"4.5","worstRating":"0"},"author":"Simon Difford","datePublished":"2016-07-25 12:40:39","description":"This drink may look fluffy and sweet but it's dry and lightly spiced. Perfect for a sunny afternoon.","glassWare":"Old-fashioned glass","image":"https://cdn.diffords.com/contrib/stock-images/2018/05/5af3008a6cdfe.jpg","keywords":["Drink","Cocktail","Recipe"],"name":"Coquetail Au Vanille","nutrition":{"@type":"NutritionInformation","calories":"149 calories"},"prepTime":"PT02M0S","recipeCategory":"Drink","recipeCuisine":"Cocktail","recipeIngredient":["60 ml White (charcoal-filtered) 1-4 year old light rum (infused with vanilla)","7.5 ml Falernum liqueur"],"recipeInstructions":[{"@type":"HowToStep","text":"SHAKE all ingredients with ice and strain into glass filled with crushed ice"},{"@type":"HowToStep","text":"Serve with straws"}],"recipeYield":"1","slug":"coquetail-au-vanille","standardDrinks":"2","totalTime":"PT02M0S","url":"https://www.diffordsguide.com/en-au/cocktails/recipe/592/coquetail-au-vanille"}