{"@context":"https://schema.org","@type":"Recipe","aggregateRating":{"@type":"AggregateRating","bestRating":"5","ratingCount":11,"ratingValue":"3.0","worstRating":"0"},"author":"Simon Difford","datePublished":"2017-03-26 08:18:47","description":"Not that special, but certainly OK.","glassWare":"Old-fashioned glass","image":"https://cdn.diffords.com/contrib/stock-images/2018/05/5af300e4287b0.jpg","keywords":["Drink","Cocktail","Recipe"],"name":"Cuban Special","nutrition":{"@type":"NutritionInformation","calories":"177 calories"},"prepTime":"PT02M0S","recipeCategory":"Drink","recipeCuisine":"Cocktail","recipeIngredient":["45 ml White (charcoal-filtered) 1-4 year old light rum","22.5 ml Triple sec liqueur (40% alc./vol.)","60 ml Pineapple juice (fresh pressed)","7.5 ml Lime juice (freshly squeezed)"],"recipeInstructions":[{"@type":"HowToStep","text":"SHAKE ingredients with ice and strain into ice-filled glass"}],"recipeYield":"1","slug":"cuban-special","standardDrinks":"2.2","totalTime":"PT02M0S","url":"https://www.diffordsguide.com/en-au/cocktails/recipe/497/cuban-special"}