{"@context":"https://schema.org","@type":"Recipe","aggregateRating":{"@type":"AggregateRating","bestRating":"5","ratingCount":16,"ratingValue":"4.0","worstRating":"0"},"author":"Simon Difford","datePublished":"2016-07-26 08:50:37","description":"Despite the absence of citrus vodka, orange liqueur and cranberry, this delicate blend is still Cosmopolitan-esque in style.","glassWare":"Coupe glass","image":"https://cdn.diffords.com/contrib/stock-images/2018/05/5af302eaba027.jpg","keywords":["Drink","Cocktail","Recipe"],"name":"Elderflower Cosmo","nutrition":{"@type":"NutritionInformation","calories":"159 calories"},"prepTime":"PT04M0S","recipeCategory":"Drink","recipeCuisine":"Cocktail","recipeIngredient":["45 ml Vodka","30 ml Elderflower liqueur","20 ml Pineapple juice (fresh pressed)","7.5 ml Lime juice (freshly squeezed)"],"recipeInstructions":[{"@type":"HowToStep","text":"SHAKE all ingredients with ice and fine strain into chilled glass"}],"recipeYield":"1","slug":"elderflower-cosmo","standardDrinks":"1.9","totalTime":"PT04M0S","url":"https://www.diffordsguide.com/en-au/cocktails/recipe/2640/elderflower-cosmo"}