{"@context":"https://schema.org","@type":"Recipe","aggregateRating":{"@type":"AggregateRating","bestRating":"5","ratingCount":5,"ratingValue":"4.0","worstRating":"0"},"author":"Mickael Perron","datePublished":"2016-07-29 16:15:00","description":"Dry and aromatic, although not for all tastes.","glassWare":"Martini glass","image":"https://cdn.diffords.com/contrib/stock-images/2018/05/5af30311448d8.jpg","keywords":["Drink","Cocktail","Recipe"],"name":"Elysian","nutrition":{"@type":"NutritionInformation","calories":"215 calories"},"prepTime":"PT02M0S","recipeCategory":"Drink","recipeCuisine":"Cocktail","recipeIngredient":["60 ml Calvados \u0026 straight applejacks","15 ml Rosso/rouge (sweet) vermouth","15 ml Dry vermouth","7.5 ml Maple syrup","3 Angostura or other aromatic bitters","3 Peychaud's or other Creole-style bitters"],"recipeInstructions":[{"@type":"HowToStep","text":"STIR all ingredients with ice and strain into chilled glass"}],"recipeYield":"1","slug":"elysian","standardDrinks":"2.5","totalTime":"PT02M0S","url":"https://www.diffordsguide.com/en-au/cocktails/recipe/2646/elysian"}