{"@context":"https://schema.org","@type":"Recipe","aggregateRating":{"@type":"AggregateRating","bestRating":"5","ratingCount":243,"ratingValue":"5.0","worstRating":"0"},"author":"Dick Bradsell","datePublished":"2018-05-04 11:58:27","description":"Forget the 'Vodka Red Bull', this is the cocktail connoisseur's way of combining caffeine and vodka.","glassWare":"Martini glass","image":"https://cdn.diffords.com/contrib/stock-images/2018/5/58/20185b95503ffb875a282976db20c141741a.jpg","keywords":["Drink","Cocktail","Recipe","coffee martini","espresso cocktail","expresso martini"],"name":"Espresso Martini","nutrition":{"@type":"NutritionInformation","calories":"160 calories"},"prepTime":"PT04M0S","recipeCategory":"Drink","recipeCuisine":"Cocktail","recipeIngredient":["45 ml Vodka","30 ml Espresso coffee (freshly made \u0026 hot)","20 ml Coffee liqueur","2 Saline solution 4:1 (20g sea salt to 80g water) (optional)"],"recipeInstructions":[{"@type":"HowToStep","text":"SHAKE all ingredients with ice and fine strain into chilled glass"}],"recipeYield":"1","slug":"espresso-martini","standardDrinks":"1.8","totalTime":"PT04M0S","url":"https://www.diffordsguide.com/en-au/cocktails/recipe/725/espresso-martini"}