{"@context":"https://schema.org","@type":"Recipe","aggregateRating":{"@type":"AggregateRating","bestRating":"5","ratingCount":5,"ratingValue":"4.0","worstRating":"0"},"author":"Francis Timmons","datePublished":"2016-07-29 17:03:46","description":"A light, fruity drink for a summer afternoon.","glassWare":"Old-fashioned glass","image":"https://cdn.diffords.com/contrib/stock-images/2016/7/03/20168f1cfca40b3d89512ba848fca7e50f5a.jpg","keywords":["Drink","Cocktail","Recipe"],"name":"Extradition","nutrition":{"@type":"NutritionInformation","calories":"188 calories"},"prepTime":"PT03M0S","recipeCategory":"Drink","recipeCuisine":"Cocktail","recipeIngredient":["3 Strawberries (hulled, small \u0026 ripe)","60 ml Pisco","60 ml Apple juice (apple cider) unsweetened \u0026 cloudy","22.5 ml Passion fruit syrup"],"recipeInstructions":[{"@type":"HowToStep","text":"MUDDLE strawberries in base of shaker"},{"@type":"HowToStep","text":"Add other ingredients, SHAKE with ice and fine strain into ice-filled glass"}],"recipeYield":"1","slug":"extradition","standardDrinks":"1.9","totalTime":"PT03M0S","url":"https://www.diffordsguide.com/en-au/cocktails/recipe/734/extradition"}