{"@context":"https://schema.org","@type":"Recipe","aggregateRating":{"@type":"AggregateRating","bestRating":"5","ratingCount":10,"ratingValue":"4.0","worstRating":"0"},"author":"Simon Difford","datePublished":"2020-08-07 07:28:11","description":"Faintly bittersweet and refreshingly citrusy.\rA riff on the classic French 75 named for the 40 botanicals that flavour Amaro Montenegro.","glassWare":"Collins glass","image":"https://cdn.diffords.com/contrib/stock-images/2020/08/5f2d17a4ce2e0.jpg","keywords":["Drink","Cocktail","Recipe","Montenegro 75"],"name":"French 40","nutrition":{"@type":"NutritionInformation","calories":"208 calories"},"prepTime":"PT04M0S","recipeCategory":"Drink","recipeCuisine":"Cocktail","recipeIngredient":["30 ml Gin","22.5 ml Amaro - Montenegro","15 ml Lemon juice (freshly squeezed)","10 ml Sugar syrup 'rich' (2 sugar to 1 water, 65.0°brix)","75 ml Brut champagne or sparkling wine"],"recipeInstructions":[{"@type":"HowToStep","text":"SHAKE first 3 ingredients and strain into ice-filled glass whilst also pouring sparkling wine"}],"recipeYield":"1","slug":"french-40","standardDrinks":"2.2","totalTime":"PT04M0S","url":"https://www.diffordsguide.com/en-au/cocktails/recipe/5580/french-40"}