{"@context":"https://schema.org","@type":"Recipe","aggregateRating":{"@type":"AggregateRating","bestRating":"5","ratingCount":24,"ratingValue":"4.5","worstRating":"0"},"author":"Simon Difford","datePublished":"2016-08-04 12:48:19","description":"A classic Dry Martini without bitters and garnished with cocktail onions in place of an olive or a twist. On those two distinctions, all are agreed. However, this cocktail's history and the best proportions of the two ingredients are topics of bar debate. I believe two different Mr Gibsons, a decade apart, were involved in creating and defining this cocktail. As for the proportions, I favour my go-to 5:1 Dry stirred Martini ratio.","glassWare":"Coupe glass","image":"https://cdn.diffords.com/contrib/stock-images/2022/04/625024302b11e.jpg","keywords":["Drink","Cocktail","Recipe"],"name":"Gibson Dry Martini","nutrition":{"@type":"NutritionInformation","calories":"149 calories"},"prepTime":"PT03M0S","recipeCategory":"Drink","recipeCuisine":"Cocktail","recipeIngredient":["62.5 ml Gin","12.5 ml Dry vermouth"],"recipeInstructions":[{"@type":"HowToStep","text":"STIR all ingredients with ice and strain into chilled glass"}],"recipeYield":"1","slug":"gibson-dry-martini","standardDrinks":"2.4","totalTime":"PT03M0S","url":"https://www.diffordsguide.com/en-au/cocktails/recipe/830/gibson-dry-martini"}