{"@context":"https://schema.org","@type":"Recipe","aggregateRating":{"@type":"AggregateRating","bestRating":"5","ratingCount":14,"ratingValue":"3.5","worstRating":"0"},"author":"Julian Gibbs","datePublished":"2016-08-05 08:31:14","description":"This serious, bourbon based cocktail ranks alongside the Sazerac in its aromatic complexity.","glassWare":"Coupe glass","image":"https://cdn.diffords.com/contrib/stock-images/2018/05/5af3056b6ddae.jpg","keywords":["Drink","Cocktail","Recipe"],"name":"Glenn's Bride","nutrition":{"@type":"NutritionInformation","calories":"200 calories"},"prepTime":"PT02M0S","recipeCategory":"Drink","recipeCuisine":"Cocktail","recipeIngredient":["60 ml Whiskey - Bourbon whiskey","30 ml Elderflower liqueur","2 Angostura or other aromatic bitters","2.5 ml Rose water"],"recipeInstructions":[{"@type":"HowToStep","text":"SHAKE all ingredients with ice and fine strain into chilled glass"}],"recipeYield":"1","slug":"glenns-bride","standardDrinks":"2.4","totalTime":"PT02M0S","url":"https://www.diffordsguide.com/en-au/cocktails/recipe/2670/glenns-bride"}