{"@context":"https://schema.org","@type":"Recipe","aggregateRating":{"@type":"AggregateRating","bestRating":"5","ratingCount":22,"ratingValue":"4.5","worstRating":"0"},"author":"Mrs Emily Cooper","datePublished":"2016-11-07 12:04:13","description":"The classic pineapple and coconut combo with a touch of rum funk and subdued apricot.\r\rSmashes are usually short drinks that include muddled mint. Strictly according to cocktail family rules, this drink might be misnamed, but like all the miss-named fruit \"Martinis\" that are not actually Martinis, it's tasty and has mass-market appeal.","glassWare":"Sling glass","image":"https://cdn.diffords.com/contrib/stock-images/2020/08/5f2d7bc092ebe.jpg","keywords":["Drink","Cocktail","Recipe"],"name":"Goombay Smash","nutrition":{"@type":"NutritionInformation","calories":"184 calories"},"prepTime":"PT04M0S","recipeCategory":"Drink","recipeCuisine":"Cocktail","recipeIngredient":["30 ml Jamaican aged blended rum","30 ml Coconut rum liqueur (35-40% alc./vol.)","15 ml Apricot (brandy) liqueur","45 ml Pineapple juice (fresh pressed)","30 ml Orange juice (freshly squeezed)","10 ml Lime juice (freshly squeezed)","2 Angostura or other aromatic bitters"],"recipeInstructions":[{"@type":"HowToStep","text":"SHAKE all ingredients with ice and strain into ice-filled glass"}],"recipeYield":"1","slug":"goombay-smash","standardDrinks":"2.4","totalTime":"PT04M0S","url":"https://www.diffordsguide.com/en-au/cocktails/recipe/887/goombay-smash"}