{"@context":"https://schema.org","@type":"Recipe","aggregateRating":{"@type":"AggregateRating","bestRating":"5","ratingCount":4,"ratingValue":"4.0","worstRating":"0"},"author":"Claire Smith","datePublished":"2017-01-17 11:57:31","description":"A fresh and refreshing orange and vanilla influenced Vodkatini.","glassWare":"Martini glass","image":"https://cdn.diffords.com/contrib/stock-images/2018/05/5af306ba930bd.jpg","keywords":["Drink","Cocktail","Recipe"],"name":"Hemingway Martini","nutrition":{"@type":"NutritionInformation","calories":"184 calories"},"prepTime":"PT02M0S","recipeCategory":"Drink","recipeCuisine":"Cocktail","recipeIngredient":["60 ml Vodka - Orange flavoured vodka","7.5 ml Vanilla liqueur","30 ml Pink grapefruit juice (freshly squeezed)","7.5 ml Dry vermouth","7.5 ml Maraschino (Marasca) syrup (from cherry jar)"],"recipeInstructions":[{"@type":"HowToStep","text":"SHAKE all ingredients with ice and fine strain into chilled glass"}],"recipeYield":"1","slug":"hemingway-martini","standardDrinks":"2.1","totalTime":"PT02M0S","url":"https://www.diffordsguide.com/en-au/cocktails/recipe/2685/hemingway-martini"}