{"@context":"https://schema.org","@type":"Recipe","aggregateRating":{"@type":"AggregateRating","bestRating":"5","ratingCount":13,"ratingValue":"4.5","worstRating":"0"},"author":"Simon Difford","datePublished":"2017-04-12 13:42:34","description":"Rich honey balances tart lemon juice over a characterful rum-base. Most recipes omit the orange juice, but as David Embury says in his Bee's Knees recipe (more from him below), \"The addition of a small amount of orange juice (about 1 to 2 parts) makes for an interesting variation.\" The additional subtle fruitiness also sits well with Jamaican rum funk.","glassWare":"Coupe glass","image":"https://cdn.diffords.com/contrib/stock-images/2021/09/614498fb3f851.jpg","keywords":["Drink","Cocktail","Recipe"],"name":"Honey Bee","nutrition":{"@type":"NutritionInformation","calories":"160 calories"},"prepTime":"PT03M0S","recipeCategory":"Drink","recipeCuisine":"Cocktail","recipeIngredient":["60 ml Jamaican aged blended rum","15 ml Lemon juice (freshly squeezed)","15 ml Honey syrup (3 honey to 1 water)","7.5 ml Orange juice (freshly squeezed) (optional)"],"recipeInstructions":[{"@type":"HowToStep","text":"SHAKE all ingredients with ice and fine strain into chilled glass"}],"recipeYield":"1","slug":"honey-bee","standardDrinks":"1.9","totalTime":"PT03M0S","url":"https://www.diffordsguide.com/en-au/cocktails/recipe/962/honey-bee"}