{"@context":"https://schema.org","@type":"Recipe","aggregateRating":{"@type":"AggregateRating","bestRating":"5","ratingCount":19,"ratingValue":"4.5","worstRating":"0"},"author":"Simon Difford","datePublished":"2021-03-15 09:25:36","description":"Simple but surprisingly delicious and very refreshing thanks to cleansing lime sourness.","glassWare":"Collins glass","image":"https://cdn.diffords.com/contrib/stock-images/2021/03/6051d41e6f0ad.jpg","keywords":["Drink","Cocktail","Recipe"],"name":"Irish Buck","nutrition":{"@type":"NutritionInformation","calories":"119 calories"},"prepTime":"PT04M0S","recipeCategory":"Drink","recipeCuisine":"Cocktail","recipeIngredient":["45 ml Irish whiskey","7.5 ml Lime juice (freshly squeezed)","105 ml Ginger ale"],"recipeInstructions":[{"@type":"HowToStep","text":"POUR all ingredients into ice-filled glass and briefly stir"}],"recipeYield":"1","slug":"irish-buck","standardDrinks":"1.5","totalTime":"PT04M0S","url":"https://www.diffordsguide.com/en-au/cocktails/recipe/7883/irish-buck"}