{"@context":"https://schema.org","@type":"Recipe","aggregateRating":{"@type":"AggregateRating","bestRating":"5","ratingCount":47,"ratingValue":"5.0","worstRating":"0"},"author":"Simon Difford","datePublished":"2020-02-28 16:11:59","description":"Blended Irish whiskey replaces richer bourbon in this mellow yet dry riff on the classic Boulevardier.","glassWare":"Old-fashioned glass","image":"https://cdn.diffords.com/contrib/stock-images/2020/02/5e59406816ab1.jpg","keywords":["Drink","Cocktail","Recipe"],"name":"Irish Boulevardier","nutrition":{"@type":"NutritionInformation","calories":"120 calories"},"prepTime":"PT02M0S","recipeCategory":"Drink","recipeCuisine":"Cocktail","recipeIngredient":["30 ml Italian red bitter liqueur","30 ml Irish whiskey","30 ml Rosso/rouge (sweet) vermouth"],"recipeInstructions":[{"@type":"HowToStep","text":"STIR all ingredients in ice-filled serving glass"}],"recipeYield":"1","slug":"irish-boulevardier","standardDrinks":"2","totalTime":"PT02M0S","url":"https://www.diffordsguide.com/en-au/cocktails/recipe/4990/irish-boulevardier"}