{"@context":"https://schema.org","@type":"Recipe","aggregateRating":{"@type":"AggregateRating","bestRating":"5","ratingCount":12,"ratingValue":"4.0","worstRating":"0"},"author":"Simon Difford","datePublished":"2020-09-02 08:08:14","description":"Bittersweet with rich jammy apricot and a touch of tart citrus freshness, this cocktail teeters on being sweet but manages to remain balanced.","glassWare":"Nick \u0026 Nora glass","image":"https://cdn.diffords.com/contrib/stock-images/2020/09/5f4f5d06265e2.jpg","keywords":["Drink","Cocktail","Recipe"],"name":"Jim Jam","nutrition":{"@type":"NutritionInformation","calories":"132 calories"},"prepTime":"PT04M0S","recipeCategory":"Drink","recipeCuisine":"Cocktail","recipeIngredient":["30 ml Averna Amaro","15 ml Apricot (brandy) liqueur","15 ml Lemon juice (freshly squeezed)"],"recipeInstructions":[{"@type":"HowToStep","text":"SHAKE all ingredients with ice and fine strain into chilled glass"}],"recipeYield":"1","slug":"jim-jam","standardDrinks":"1.2","totalTime":"PT04M0S","url":"https://www.diffordsguide.com/en-au/cocktails/recipe/5806/jim-jam"}