{"@context":"https://schema.org","@type":"Recipe","aggregateRating":{"@type":"AggregateRating","bestRating":"5","ratingCount":2,"ratingValue":"4.0","worstRating":"0"},"author":"Regis Laacher","datePublished":"2018-02-01 09:04:26","description":"A dry, bitter apéritif-style riff on the classic French 75. Try with a splash more sparkling wine than suggested in the recipe and/or a spoon of sugar syrup.","glassWare":"Wine glass","image":"https://cdn.diffords.com/contrib/stock-images/2018/05/5af3097a075a1.jpg","keywords":["Drink","Cocktail","Recipe"],"name":"Le Very French 75","nutrition":{"@type":"NutritionInformation","calories":"170 calories"},"prepTime":"PT02M0S","recipeCategory":"Drink","recipeCuisine":"Cocktail","recipeIngredient":["30 ml Gentian liqueur (e.g. Suze, Salers etc)","30 ml Lillet Rouge","15 ml Lemon juice (freshly squeezed)","25 ml Gin","30 ml Brut champagne or sparkling wine"],"recipeInstructions":[{"@type":"HowToStep","text":"SHAKE first 4 ingredients with ice and fine strain into chilled glass"},{"@type":"HowToStep","text":"TOP with champagne"}],"recipeYield":"1","slug":"le-very-french-75","standardDrinks":"1.6","totalTime":"PT02M0S","url":"https://www.diffordsguide.com/en-au/cocktails/recipe/4357/le-very-french-75"}