{"@context":"https://schema.org","@type":"Recipe","aggregateRating":{"@type":"AggregateRating","bestRating":"5","ratingCount":17,"ratingValue":"4.5","worstRating":"0"},"author":"Victor Bergeron A.K.A Trader Vic","datePublished":"2017-01-04 17:25:07","description":"Originally sweetened with sugar syrup, this is better smoothed with honey.","glassWare":"Coupe glass","image":"https://cdn.diffords.com/contrib/stock-images/2022/01/61eaa0a518483.jpg","keywords":["Drink","Cocktail","Recipe"],"name":"Maria Theresa Margarita","nutrition":{"@type":"NutritionInformation","calories":"178 calories"},"prepTime":"PT04M0S","recipeCategory":"Drink","recipeCuisine":"Cocktail","recipeIngredient":["60 ml Tequila reposado","30 ml Cranberry juice (sweetened)","15 ml Lime juice (freshly squeezed)","10 ml Agave syrup"],"recipeInstructions":[{"@type":"HowToStep","text":"SHAKE all ingredients with ice and fine strain into chilled glass"}],"recipeYield":"1","slug":"maria-theresa-margarita","standardDrinks":"1.9","totalTime":"PT04M0S","url":"https://www.diffordsguide.com/en-au/cocktails/recipe/1259/maria-theresa-margarita"}