{"@context":"https://schema.org","@type":"Recipe","aggregateRating":{"@type":"AggregateRating","bestRating":"5","ratingCount":2,"ratingValue":"4.0","worstRating":"0"},"author":"Simon Difford","datePublished":"2020-11-17 13:42:40","description":"Best enjoyed on a sunny summer's afternoon. Tonic water dries and invigorates this fruity cooler.","glassWare":"Copa glass","image":"https://cdn.diffords.com/contrib/stock-images/2020/11/5fb3eadf878e0.jpg","keywords":["Drink","Cocktail","Recipe"],"name":"Mediterranean Cooler","nutrition":{"@type":"NutritionInformation","calories":"59 calories"},"prepTime":"PT03M0S","recipeCategory":"Drink","recipeCuisine":"Cocktail","recipeIngredient":["25 ml Strawberry flavoured vodka","25 ml Tawny port","110 ml Mediterranean tonic water "],"recipeInstructions":[{"@type":"HowToStep","text":"POUR all ingredients into ice-filled glass and briefly stir"}],"recipeYield":"1","slug":"mediterranean-cooler","standardDrinks":"1.2","totalTime":"PT03M0S","url":"https://www.diffordsguide.com/en-au/cocktails/recipe/6442/mediterranean-cooler"}