{"@context":"https://schema.org","@type":"Recipe","aggregateRating":{"@type":"AggregateRating","bestRating":"5","ratingCount":17,"ratingValue":"4.0","worstRating":"0"},"author":"Frank Meier","datePublished":"2017-06-02 11:45:33","description":"Great when made with freshly squeezed orange juice, this cocktail is very similar to the Buck's Fizz, which tends to have a higher proportion of champagne. Also see the Grand Mimosa, basically the same drink charged with orange liqueur.","glassWare":"Goblet glass","image":"https://cdn.diffords.com/contrib/stock-images/2019/10/5dad832458385.jpg","keywords":["Drink","Cocktail","Recipe"],"name":"Mimosa","nutrition":{"@type":"NutritionInformation","calories":"67 calories"},"prepTime":"PT02M0S","recipeCategory":"Drink","recipeCuisine":"Cocktail","recipeIngredient":["90 ml Brut champagne or sparkling wine (chilled)","90 ml Orange juice (freshly squeezed) (chilled)"],"recipeInstructions":[{"@type":"HowToStep","text":"POUR half the champagne into ice-filled glass (preferably a chunk of block ice), then POUR orange juice and finally the rest of the champagne"}],"recipeYield":"1","slug":"mimosa","standardDrinks":"1","totalTime":"PT02M0S","url":"https://www.diffordsguide.com/en-au/cocktails/recipe/1324/mimosa"}