{"@context":"https://schema.org","@type":"Recipe","aggregateRating":{"@type":"AggregateRating","bestRating":"5","ratingCount":10,"ratingValue":"3.5","worstRating":"0"},"author":"Simon Difford","datePublished":"2016-12-13 20:14:10","description":"A pink, fruity, creamy concoction.","glassWare":"Coupe glass","image":"https://cdn.diffords.com/contrib/stock-images/2018/05/5af30c01e9181.jpg","keywords":["Drink","Cocktail","Recipe"],"name":"Miss Martini","nutrition":{"@type":"NutritionInformation","calories":"231 calories"},"prepTime":"PT04M0S","recipeCategory":"Drink","recipeCuisine":"Cocktail","recipeIngredient":["7 Raspberries (fresh)","60 ml Vodka","15 ml Black raspberry liqueur (e.g. Chambord)","5 ml Sugar syrup 'rich' (2 sugar to 1 water, 65.0°brix)","15 ml Single cream / half-and-half"],"recipeInstructions":[{"@type":"HowToStep","text":"MUDDLE raspberries in base of shaker"},{"@type":"HowToStep","text":"Add other ingredients, SHAKE with ice and fine strain into chilled glass"}],"recipeYield":"1","slug":"miss-martini","standardDrinks":"2.1","totalTime":"PT04M0S","url":"https://www.diffordsguide.com/en-au/cocktails/recipe/1333/miss-martini"}