{"@context":"https://schema.org","@type":"Recipe","aggregateRating":{"@type":"AggregateRating","bestRating":"5","ratingCount":32,"ratingValue":"4.0","worstRating":"0"},"author":"Simon Difford","datePublished":"2020-08-07 07:09:59","description":"Bittersweet, spicy and enlivening.","glassWare":"Copper mug or Collins glass","image":"https://cdn.diffords.com/contrib/stock-images/2020/08/5f2d1744ea6c4.jpg","keywords":["Drink","Cocktail","Recipe"],"name":"Monte Mule","nutrition":{"@type":"NutritionInformation","calories":"180 calories"},"prepTime":"PT04M0S","recipeCategory":"Drink","recipeCuisine":"Cocktail","recipeIngredient":["45 ml Amaro - Montenegro","20 ml Lime juice (freshly squeezed)","135 ml Ginger beer"],"recipeInstructions":[{"@type":"HowToStep","text":"POUR all ingredients into ice-filled mug/glass and briefly stir"}],"recipeYield":"1","slug":"monte-mule","standardDrinks":"0.9","totalTime":"PT04M0S","url":"https://www.diffordsguide.com/en-au/cocktails/recipe/5578/monte-mule"}