{"@context":"https://schema.org","@type":"Recipe","aggregateRating":{"@type":"AggregateRating","bestRating":"5","ratingCount":12,"ratingValue":"4.5","worstRating":"0"},"author":"Trinh Quan Huy-Philip","datePublished":"2018-02-09 09:56:05","description":"A riff on the classic Negroni from Vietnam which brilliantly set the richness of sloe gin against bone dry fino sherry while harnessing the herbal bitterness of gentian. Hit the right dilution, and by the third sip, when your palate has adjusted, you'll not be able to stop sipping this bitter aperitif cocktail.","glassWare":"Old-fashioned glass","image":"https://cdn.diffords.com/contrib/stock-images/2018/05/5af30cbed775b.jpg","keywords":["Drink","Cocktail","Recipe"],"name":"Negrino","nutrition":{"@type":"NutritionInformation","calories":"154 calories"},"prepTime":"PT03M0S","recipeCategory":"Drink","recipeCuisine":"Cocktail","recipeIngredient":["40 ml Sloe gin liqueur","30 ml Fino sherry","20 ml Gentian liqueur (e.g. Suze, Salers etc)"],"recipeInstructions":[{"@type":"HowToStep","text":"POUR all ingredients into ice-filled glass and STIR"}],"recipeYield":"1","slug":"negrino","standardDrinks":"1.3","totalTime":"PT03M0S","url":"https://www.diffordsguide.com/en-au/cocktails/recipe/4295/negrino"}