{"@context":"https://schema.org","@type":"Recipe","aggregateRating":{"@type":"AggregateRating","bestRating":"5","ratingCount":2,"ratingValue":"3.5","worstRating":"0"},"author":"Simon Difford","datePublished":"2016-12-14 13:32:08","description":"Raspberry is the predominant flavour in this long drink.","glassWare":"Collins glass","image":"https://cdn.diffords.com/contrib/stock-images/2018/05/5af30cfcebc56.jpg","keywords":["Drink","Cocktail","Recipe"],"name":"New Orleans Punch","nutrition":{"@type":"NutritionInformation","calories":"338 calories"},"prepTime":"PT02M0S","recipeCategory":"Drink","recipeCuisine":"Cocktail","recipeIngredient":["45 ml Bourbon whiskey","22.5 ml Caribbean blended rum aged 6-10 years","45 ml Black raspberry liqueur (e.g. Chambord)","45 ml Lemon juice (freshly squeezed)","90 ml Camomile tea (cold)"],"recipeInstructions":[{"@type":"HowToStep","text":"SHAKE all ingredients with ice and strain into glass filled with crushed ice"},{"@type":"HowToStep","text":"Serve with straws"}],"recipeYield":"1","slug":"new-orleans-punch","standardDrinks":"2.8","totalTime":"PT02M0S","url":"https://www.diffordsguide.com/en-au/cocktails/recipe/1396/new-orleans-punch"}