{"@context":"https://schema.org","@type":"Recipe","aggregateRating":{"@type":"AggregateRating","bestRating":"5","ratingCount":14,"ratingValue":"4.5","worstRating":"0"},"author":"Erick Castro","datePublished":"2021-10-29 11:53:42","description":"Green Chartreuse blended with coconut and pineapple – yummm.","glassWare":"Collins glass","image":"https://cdn.diffords.com/contrib/stock-images/2021/10/617be9566b866.jpg","keywords":["Drink","Cocktail","Recipe","Chartreuse Colada","Greenya Colada"],"name":"Piña Verde","nutrition":{"@type":"NutritionInformation","calories":"230 calories"},"prepTime":"PT04M0S","recipeCategory":"Drink","recipeCuisine":"Cocktail","recipeIngredient":["45 ml Chartreuse Green","45 ml Pineapple juice (fresh pressed)","22.5 ml Cream of coconut (e.g. Coco Lopez, Re'al etc.)","15 ml Lime juice (freshly squeezed)"],"recipeInstructions":[{"@type":"HowToStep","text":"BLEND all ingredients with scoop crushed ice"}],"recipeYield":"1","slug":"pina-verde","standardDrinks":"1.8","totalTime":"PT04M0S","url":"https://www.diffordsguide.com/en-au/cocktails/recipe/10138/pina-verde"}