{"@context":"https://schema.org","@type":"Recipe","aggregateRating":{"@type":"AggregateRating","bestRating":"5","ratingCount":1,"ratingValue":"4.5","worstRating":"0"},"author":"George Bagos","datePublished":"2020-05-30 13:42:11","description":"Rich almond with delicate zesty citrus packaged in a light pink refreshing drink.","glassWare":"Collins glass","image":"https://cdn.diffords.com/contrib/stock-images/2020/07/5f058994a4e8d.jpg","keywords":["Drink","Cocktail","Recipe"],"name":"Pink Tsipouro Fizz","nutrition":{"@type":"NutritionInformation","calories":"148 calories"},"prepTime":"PT03M0S","recipeCategory":"Drink","recipeCuisine":"Cocktail","recipeIngredient":["50 ml Tsipouro","5 ml Orgeat (almond) sugar syrup","5 ml Lime juice (freshly squeezed)","100 ml Pink grapefruit soda"],"recipeInstructions":[{"@type":"HowToStep","text":"POUR first 3 ingredients into glass and STIR"},{"@type":"HowToStep","text":"Fill glass with ice and TOP with grapefruit soda"}],"recipeYield":"1","slug":"pink-tsipouro-fizz","standardDrinks":"1.8","totalTime":"PT03M0S","url":"https://www.diffordsguide.com/en-au/cocktails/recipe/5163/pink-tsipouro-fizz"}