{"@context":"https://schema.org","@type":"Recipe","aggregateRating":{"@type":"AggregateRating","bestRating":"5","ratingCount":21,"ratingValue":"4.0","worstRating":"0"},"author":"Philip Duff","datePublished":"2017-08-04 06:59:23","description":"Long and refreshing with a tart lemony bite.","glassWare":"Collins glass","image":"https://cdn.diffords.com/contrib/stock-images/2018/05/5af30fe0f0f79.jpg","keywords":["Drink","Cocktail","Recipe"],"name":"PLB","nutrition":{"@type":"NutritionInformation","calories":"57 calories"},"prepTime":"PT02M0S","recipeCategory":"Drink","recipeCuisine":"Cocktail","recipeIngredient":["1/4 Lemon (fresh) (chopped)","40 ml Limoncello liqueur","2 Angostura or other aromatic bitters","105 ml Tonic water"],"recipeInstructions":[{"@type":"HowToStep","text":"MUDDLE lemon in base of a sturdy rocks glass and then pour into serving glass"},{"@type":"HowToStep","text":"Fill glass with ice, add limoncello and bitters"},{"@type":"HowToStep","text":"TOP with tonic and lightly stir"}],"recipeYield":"1","slug":"plb","standardDrinks":"1","totalTime":"PT02M0S","url":"https://www.diffordsguide.com/en-au/cocktails/recipe/4243/plb","video":{"@type":"VideoObject","contentUrl":"https://cdn.diffords.com/contrib/videos/2017/08/5ca36157553e6.mp4","description":"Long and refreshing with a tart lemony bite.\r\u003cbr\u003e","embedUrl":"https://www.diffordsguide.com/cocktails/recipe/4243/plb","name":"HOWTO make PLB","thumbnailUrl":"https://cdn.diffords.com/contrib/videos/2017/08/5ca3615755640.jpg","uploadDate":"2017-08-04 06:59:23"}}