{"@context":"https://schema.org","@type":"Recipe","aggregateRating":{"@type":"AggregateRating","bestRating":"5","ratingCount":1,"ratingValue":"4.0","worstRating":"0"},"author":"Simon Difford","datePublished":"2017-01-04 18:28:10","description":"Sherried prunes further fortified by gin.","glassWare":"Martini glass","image":"https://cdn.diffords.com/contrib/stock-images/2018/05/5af3105873b9a.jpg","keywords":["Drink","Cocktail","Recipe"],"name":"Pruneaux","nutrition":{"@type":"NutritionInformation","calories":"194 calories"},"prepTime":"PT02M0S","recipeCategory":"Drink","recipeCuisine":"Cocktail","recipeIngredient":["45 ml Gin","30 ml Amontillado sherry","15 ml Pedro Ximénez sherry","22.5 ml Orange juice (freshly squeezed)","22.5 ml Prune syrup (from tinned fruit)"],"recipeInstructions":[{"@type":"HowToStep","text":"SHAKE all ingredients with ice and fine strain into chilled glass"}],"recipeYield":"1","slug":"pruneaux","standardDrinks":"2.1","totalTime":"PT02M0S","url":"https://www.diffordsguide.com/en-au/cocktails/recipe/1609/pruneaux"}