{"@context":"https://schema.org","@type":"Recipe","aggregateRating":{"@type":"AggregateRating","bestRating":"5","ratingCount":8,"ratingValue":"4.5","worstRating":"0"},"author":"Simon Difford","datePublished":"2021-09-23 20:45:35","description":"The high proportion of vermouth makes this Martini almost sherry-like. And I like sherry!","glassWare":"Martini glass","image":"https://cdn.diffords.com/contrib/stock-images/2022/02/61fd5841bdd3c.jpg","keywords":["Drink","Cocktail","Recipe"],"name":"Queen Martini","nutrition":{"@type":"NutritionInformation","calories":"136 calories"},"prepTime":"PT03M0S","recipeCategory":"Drink","recipeCuisine":"Cocktail","recipeIngredient":["30 ml Gin","30 ml Dry vermouth","30 ml Rosso/rouge (sweet) vermouth","1 Orange bitters"],"recipeInstructions":[{"@type":"HowToStep","text":"STIR all ingredients with ice and strain into chilled glass"}],"recipeYield":"1","slug":"queen-martini","standardDrinks":"1.8","totalTime":"PT03M0S","url":"https://www.diffordsguide.com/en-au/cocktails/recipe/9777/queen-martini"}