{"@context":"https://schema.org","@type":"Recipe","aggregateRating":{"@type":"AggregateRating","bestRating":"5","ratingCount":17,"ratingValue":"3.5","worstRating":"0"},"author":"Simon Difford","datePublished":"2017-01-05 17:41:27","description":"Long and refreshing with lime freshness and a hint of ginger.","glassWare":"Collins glass","image":"https://cdn.diffords.com/contrib/stock-images/2018/05/5af312a49be6e.jpg","keywords":["Drink","Cocktail","Recipe"],"name":"Shady Grove Cooler","nutrition":{"@type":"NutritionInformation","calories":"184 calories"},"prepTime":"PT02M0S","recipeCategory":"Drink","recipeCuisine":"Cocktail","recipeIngredient":["60 ml Gin","30 ml Lime juice (freshly squeezed)","15 ml Sugar syrup 'rich' (2 sugar to 1 water, 65.0°brix)"," Ginger ale"],"recipeInstructions":[{"@type":"HowToStep","text":"SHAKE first three ingredients with ice and strain into ice-filled glass"},{"@type":"HowToStep","text":"TOP with ginger ale, lightly stir and serve with straws"}],"recipeYield":"1","slug":"shady-grove-cooler","standardDrinks":"1.7","totalTime":"PT02M0S","url":"https://www.diffordsguide.com/en-au/cocktails/recipe/1768/shady-grove-cooler"}