{"@context":"https://schema.org","@type":"Recipe","aggregateRating":{"@type":"AggregateRating","bestRating":"5","ratingCount":8,"ratingValue":"4.0","worstRating":"0"},"author":"Vincenzo Marianella","datePublished":"2017-01-05 21:05:53","description":"Smoky, with floral and tropical fruit notes from the elderflower liqueur and added complexity from the vermouth and Cynar.","glassWare":"Martini glass","image":"https://cdn.diffords.com/contrib/stock-images/2018/05/5af3136408876.jpg","keywords":["Drink","Cocktail","Recipe"],"name":"Smoke of Scotland","nutrition":{"@type":"NutritionInformation","calories":"180 calories"},"prepTime":"PT02M0S","recipeCategory":"Drink","recipeCuisine":"Cocktail","recipeIngredient":["60 ml Whisky - Peated Scotch whisky","15 ml Dry vermouth","15 ml Elderflower liqueur","5 ml Cynar or other carciofo amaro"],"recipeInstructions":[{"@type":"HowToStep","text":"STIR all ingredients with ice and strain into chilled glass"}],"recipeYield":"1","slug":"smoke-of-scotland","standardDrinks":"2.9","totalTime":"PT02M0S","url":"https://www.diffordsguide.com/en-au/cocktails/recipe/2579/smoke-of-scotland"}