{"@context":"https://schema.org","@type":"Recipe","aggregateRating":{"@type":"AggregateRating","bestRating":"5","ratingCount":4,"ratingValue":"4.5","worstRating":"0"},"author":"Ally Marrone","datePublished":"2022-10-21 14:12:30","description":"Proof, if it were needed, that mezcal works in tropical/Tiki cocktails.","glassWare":"Old-fashioned glass","image":"https://cdn.diffords.com/contrib/stock-images/2022/10/6352b446400e9.jpg","keywords":["Drink","Cocktail","Recipe"],"name":"Snake Eyes","nutrition":{"@type":"NutritionInformation","calories":"173 calories"},"prepTime":"PT04M0S","recipeCategory":"Drink","recipeCuisine":"Cocktail","recipeIngredient":["45 ml Mezcal","60 ml Coconut water","7.5 ml Lime juice (freshly squeezed)","15 ml Sugar cane syrup (from juice)","5 ml Crème de banane liqueur"],"recipeInstructions":[{"@type":"HowToStep","text":"SHAKE all ingredients with ice and strain into ice-filled glass"}],"recipeYield":"1","slug":"snake-eyes","standardDrinks":"1.5","totalTime":"PT04M0S","url":"https://www.diffordsguide.com/en-au/cocktails/recipe/14830/snake-eyes"}