{"@context":"https://schema.org","@type":"Recipe","aggregateRating":{"@type":"AggregateRating","bestRating":"5","ratingCount":2,"ratingValue":"3.5","worstRating":"0"},"author":"Jessica Lambert","datePublished":"2021-12-24 12:50:54","description":"Stir well, dilution is key to this richly flavoured cocktail which has currant and dried fruit notes.","glassWare":"Nick \u0026 Nora glass","image":"https://cdn.diffords.com/contrib/stock-images/2022/01/61d45a2af3d72.jpg","keywords":["Drink","Cocktail","Recipe"],"name":"Spanish Armada","nutrition":{"@type":"NutritionInformation","calories":"146 calories"},"prepTime":"PT04M0S","recipeCategory":"Drink","recipeCuisine":"Cocktail","recipeIngredient":["20 ml 10+ year old blended rum","20 ml Spanish brandy","10 ml Blended Scotch whisky","5 ml Whisky - Peated Scotch whisky","5 ml Pedro Ximénez sherry","5 ml Bigallet China-China liqueur","1 Angostura or other aromatic bitters"],"recipeInstructions":[{"@type":"HowToStep","text":"STIR all ingredients with ice and strain into chilled glass"}],"recipeYield":"1","slug":"spanish-armada","standardDrinks":"1.5","totalTime":"PT04M0S","url":"https://www.diffordsguide.com/en-au/cocktails/recipe/10714/spanish-armada"}