{"@context":"https://schema.org","@type":"Recipe","aggregateRating":{"@type":"AggregateRating","bestRating":"5","ratingCount":2,"ratingValue":"4.5","worstRating":"0"},"author":"Simon Difford","datePublished":"2020-03-12 10:07:39","description":"As the name suggests, this riff on a Brandy Alexander has a delicately spicy finish that cuts through the creaminess.","glassWare":"Coupe glass","image":"https://cdn.diffords.com/contrib/stock-images/2020/03/5e6a49128b531.jpg","keywords":["Drink","Cocktail","Recipe"],"name":"Spiced Alexander","nutrition":{"@type":"NutritionInformation","calories":"245 calories"},"prepTime":"PT04M0S","recipeCategory":"Drink","recipeCuisine":"Cocktail","recipeIngredient":["45 ml Cacao \u0026 coffee spiced rum","15 ml White crème de cacao liqueur","15 ml Dark crème de cacao liqueur","22.5 ml Single cream / half-and-half","10 ml Pasteurised egg white (or aquafaba)"],"recipeInstructions":[{"@type":"HowToStep","text":"SHAKE all ingredients with ice and strain back into shaker"},{"@type":"HowToStep","text":"DRY SHAKE (without ice) and fine strain into chilled glass"}],"recipeYield":"1","slug":"spiced-alexander","standardDrinks":"2.1","totalTime":"PT04M0S","url":"https://www.diffordsguide.com/en-au/cocktails/recipe/4998/spiced-alexander"}