{"@context":"https://schema.org","@type":"Recipe","aggregateRating":{"@type":"AggregateRating","bestRating":"5","ratingCount":5,"ratingValue":"4.5","worstRating":"0"},"author":"Tommy Cummins","datePublished":"2018-03-01 18:44:43","description":"Imagine a delicately clove influenced Daiquiri but with the bready influence of poitín, then you are some way towards imagining the taste of this refreshing and invigorating cocktail.","glassWare":"Coupe glass","image":"https://cdn.diffords.com/contrib/stock-images/2018/05/5af314fc66f26.jpg","keywords":["Drink","Cocktail","Recipe"],"name":"Tara Cocktail","nutrition":{"@type":"NutritionInformation","calories":"50 calories"},"prepTime":"PT02M0S","recipeCategory":"Drink","recipeCuisine":"Cocktail","recipeIngredient":["45 ml Poteen/Poitín","15 ml Falernum liqueur","15 ml Lime juice (freshly squeezed)","3 Abbott's bitters"],"recipeInstructions":[{"@type":"HowToStep","text":"SHAKE all ingredients with ice and fine strain into chilled glass"}],"recipeYield":"1","slug":"tara-cocktail","standardDrinks":"0.2","totalTime":"PT02M0S","url":"https://www.diffordsguide.com/en-au/cocktails/recipe/4053/tara-cocktail"}