{"@context":"https://schema.org","@type":"Recipe","aggregateRating":{"@type":"AggregateRating","bestRating":"5","ratingCount":12,"ratingValue":"4.5","worstRating":"0"},"author":"Joseph Akhavan","datePublished":"2017-12-01 09:40:54","description":"Bittersweet and boozy with a dry finish. Striking the right degree of dilution is key to the success of this cocktail – stir a little longer than usual and if using ice straight from the freezer perhaps consider adding a dash of chilled water.","glassWare":"Coupe glass","image":"https://cdn.diffords.com/contrib/stock-images/2018/05/5af315e898211.jpg","keywords":["Drink","Cocktail","Recipe"],"name":"The Italian Job Cocktail","nutrition":{"@type":"NutritionInformation","calories":"194 calories"},"prepTime":"PT02M0S","recipeCategory":"Drink","recipeCuisine":"Cocktail","recipeIngredient":["22.5 ml Overproof pot still rum","22.5 ml Americano Bianco","22.5 ml Bittersweet orange-red aperitivo","22.5 ml Byrrh aperitif aromatised wine","2 Orange bitters"],"recipeInstructions":[{"@type":"HowToStep","text":"STIR all the ingredients with ice and strain into chilled glass"}],"recipeYield":"1","slug":"the-italian-job-cocktail","standardDrinks":"1.7","totalTime":"PT02M0S","url":"https://www.diffordsguide.com/en-au/cocktails/recipe/4311/the-italian-job-cocktail"}