{"@context":"https://schema.org","@type":"Recipe","aggregateRating":{"@type":"AggregateRating","bestRating":"5","ratingCount":24,"ratingValue":"5.0","worstRating":"0"},"author":"Ryan Chetiyawardana","datePublished":"2019-09-05 15:51:31","description":"Peaty smoky whisky subtly influences this complex and silky-smooth rum flip.","glassWare":"Coupe glass","image":"https://cdn.diffords.com/contrib/stock-images/2019/09/5d7256e531d47.jpg","keywords":["Drink","Cocktail","Recipe"],"name":"Three Storms Flip","nutrition":{"@type":"NutritionInformation","calories":"206 calories"},"prepTime":"PT03M0S","recipeCategory":"Drink","recipeCuisine":"Cocktail","recipeIngredient":["50 ml White/gold 1-3 year old mellow light rum","25 ml Falernum liqueur","7.5 ml Whisky - Peated Scotch whisky","2 Orange bitters","2 Saline solution 4:1 (20g sea salt to 80g water)","1 Black pepper","1 Egg (white \u0026 yolk)"],"recipeInstructions":[{"@type":"HowToStep","text":"SHAKE all ingredients with ice and fine strain into chilled glass"}],"recipeYield":"1","slug":"three-storms-flip","standardDrinks":"2.3","totalTime":"PT03M0S","url":"https://www.diffordsguide.com/en-au/cocktails/recipe/4832/three-storms-flip"}